{"adjective": "квакающий", "features": ["быть похожим на сказку", "плохо заканчиваться", "иметь одного персонажа"], "model": "google/gemma-2-27b-it bnb_4bit", "noun": "мудрость", "sha3_256": "05026db09241863c8c04deeeca4f8930e88fc6bcc2329fa73f963001fb41ca18", "story": "Жила-была маленькая лягушка. Она была зеленая и очень любила греться на солнышке. Лягушка прыгала по траве, ловила мух и грелась на теплых камнях. Однажды лягушка услышала квакающий голос.\n\n\"Привет, лягушка!\" - сказал голос. Лягушка посмотрела и увидела большую, старую лягушку. \"Я знаю много мудрости,\" - сказала старая лягушка. \"Я могу научить тебя всему, что знаю.\" Лягушка обрадовалась. Она хотела знать все!\n\nСтарая лягушка сказала лягушке: \"Чтобы узнать мудрость, нужно съесть волшебный гриб.\" Лягушка поверила старой лягушке и съела гриб. Но гриб был не волшебный, а ядовитый! Лягушка почувствовала себя плохо.\n\nОна стала слабой и не могла прыгать. Старая лягушка просто упрыгнула и исчезла. Лягушка лежала на траве, очень грустная. Она так хотела узнать мудрость, но теперь ей было очень плохо.", "verb": "греться"}