{"adjective": "большой", "features": ["быть похожим на сказку", "иметь неожиданный поворот сюжета", "содержать диалог", "иметь трёх персонажей"], "model": "google/gemma-2-27b-it bnb_4bit", "noun": "солнце", "sha3_256": "136023c603c58c2af579009e5c31275dc46a793ac4d1a524fa905e2105511b91", "story": "Жила-была маленькая птичка. Она любила сидеть на ветке и петь песенки. Однажды птичка увидела большое солнце. Оно светило ярко-ярко и грело птичку.\n\n\"Солнце, солнце, ты такое большое!\" - сказала птичка. \"Ты улетаешь высоко-высоко?\"\n\nСолнце улыбнулось. \"Да, птичка, я улетаю высоко-высоко, к облакам. Там я играю с лучиками.\"\n\nПтичка очень хотела посмотреть на лучики. \"Можно я полечу с тобой?\" - спросила она.\n\nСолнце покачало головой. \"Нет, птичка, ты не сможешь полететь так высоко. Но я могу подарить тебе лучик!\"\n\nИ солнце оторвало маленький лучик и подарило его птичке. Птичка была очень рада. Теперь у нее был свой маленький лучик, который светил ей всегда.", "verb": "улетать"}