{"adjective": "музыкальный", "features": ["иметь неожиданный поворот сюжета", "быть похожим на сказку", "иметь хороший конец", "содержать диалог", "иметь трёх персонажей"], "model": "google/gemma-2-27b-it bnb_4bit", "noun": "полицейский", "sha3_256": "1afd59f06762d997ec64401c80c06d0a4c302c547648fafef157db656757249c", "story": "Жила-была маленькая девочка Маша. Она очень любила цветы. Маша каждый день ходила в сад и удобряла свои цветочки.  \n\nОднажды, когда Маша удобряла свои розы, к ней подошел полицейский. Он был большой и сильный, с блестящим значком на груди. \"Привет, Маша!\" - сказал полицейский. \"Что ты делаешь?\"\n\n\"Я удобряю свои розы,\" - ответила Маша. \"Они такие красивые!\"\n\n\"А ты знаешь,\" - сказал полицейский, \"что розы любят музыку? Они растут лучше, если слышать красивые песни!\"\n\nМаша удивилась. \"Музыка для роз?\" - спросила она.\n\nПолицейский улыбнулся. \"Да, да! Послушай!\" Он достал из кармана маленькую флейту и заиграл веселую, музыкальную мелодию. Розы затрепетали от радости, а Маша затанцевала. С тех пор Маша всегда играла музыку для своих роз, и они росли самыми красивыми и ароматными во всем саду!", "verb": "удобрять"}