{"adjective": "неверный", "features": ["иметь хороший конец", "иметь одного персонажа"], "model": "google/gemma-2-27b-it bnb_4bit", "noun": "теннисный корт", "sha3_256": "21dcbe2b141805d23f2beb82f6f6e85e9e0754feed5986a1d74a3ab40bb9480a", "story": "Маша играла на теннисном корте. Она бегала и прыгала, как зайчик. Маша хотела копать в земле. Она взяла лопатку и начала копать.\n\nМаша копала и копала. Она нашла что-то странное! Это был неверный мячик для тенниса. Он был синим, а не желтым! Маша удивилась.\n\nМаша показала синюю штуку маме. Мама сказала, что это не мячик для тенниса, а просто синяя игрушка. Маша обрадовалась!\n\nТеперь у Маши есть новая игрушка! Она будет играть с ней на теннисном корте. Маша будет бегать, прыгать и бросать синюю игрушку высоко в небо!", "verb": "копать"}