{"adjective": "плавник", "features": ["содержать диалог", "плохо заканчиваться", "иметь неожиданный поворот сюжета", "иметь трёх персонажей"], "model": "google/gemma-2-27b-it bnb_4bit", "noun": "цветок", "sha3_256": "264a3ff369efc7033a81be1bd4648ff2201f73511912c699bdd6cdea77b575a5", "story": "Маша, Коля и рыбка Плюшка играли на берегу реки. Маша держала в руках большой, красивый цветок.\n\n— Смотри, Коля, какой цветок! — сказала Маша. — Красивый, да?\n\n— Да! — ответил Коля. — Я хочу его бросить в реку!\n\nМаша бросила цветок в воду. Он плыл по реке, пока не доплыл до Плюшки. Плюшка хотела взять цветок в свой рот, но он был слишком большой.\n\n— Плюшка, хочешь цветок? — спросила Маша.\n\nПлюшка кивнула головой. Вдруг, из воды выпрыгнул большой, страшный краб! У него были большие клешни и длинный, острый плавник.\n\n— Аааа! — закричали Маша и Коля. Краб схватил цветок и уплыл.", "verb": "бросать"}