{"adjective": "одинокий", "features": ["иметь неожиданный поворот сюжета", "быть поучительным"], "model": "google/gemma-2-27b-it bnb_4bit", "noun": "ярость", "sha3_256": "26b5c4931cde89614b49fd783d9e3612de08f46dd6f85e6b16bb8ac840be8bd8", "story": "Маленький щегол сидел на ветке и грустно щебетал. Он был очень одинокий. Все другие птички играли вместе, а он сидел один. Щегол рассердился. Он хотел играть, но никто не хотел играть с ним.\n\nЩегол увидел красивую бабочку. Бабочка летела и весело кружилась. Щегол захотел поймать бабочку, чтобы поиграть с ней. Он прыгнул, но бабочка улетела. Щегол расстроился. Он был очень зол.\n\nВдруг щегол услышал тихий плач. Он посмотрел вниз и увидел маленького птенчика. Птенчик упал из гнезда и не мог подняться. Щегол забыл про свою ярость и быстро полетел к птенчику.\n\nЩегол стал щебетать ласково, чтобы успокоить птенчика. Он помахал крыльями, чтобы привлечь внимание мамы-птицы. Мама-птица услышала щебетание и быстро прилетела к птенчику. Она была очень рада, что щегол помог ее малышу.\n\nЩегол понял, что помогать другим птицам - это намного лучше, чем сидеть один и злиться. Он больше не был одинокий, потому что он сделал доброе дело.", "verb": "щебетать"}