{"adjective": "нешаблонный", "features": ["быть поучительным", "иметь одного персонажа", "быть похожим на сказку"], "model": "google/gemma-2-27b-it bnb_4bit", "noun": "парикмахерская", "sha3_256": "2e0aac8c1af1e1df4050245e049b34afd72f563bd3219fcfadf43f43034db87c", "story": "Жила-была маленькая гусеница. Она очень любила шевелиться. Целый день она ползала по листикам, шевелила усиками и смотрела на мир. Однажды гусеница увидела красивую парикмахерскую. В ней работала добрая старая бабочка.\n\nГусеница зашла в парикмахерскую и спросила: \"Бабочка, сделай мне нешаблонную прическу!\". Бабочка улыбнулась и сказала: \"Конечно, маленькая! Но помни, что настоящая красота - это когда ты любишь себя такой, какая ты есть\".\n\nБабочка сделала гусенице красивую прическу. Гусеница была очень рада. Но потом она поняла, что бабочка права. Самое главное - быть собой, а не похожей на других.\n\nС тех пор гусеница больше не хотела нешаблонных причесок. Она любила шевелиться, ползать по листикам и быть просто собой - маленькой, милой гусеницей.", "verb": "шевелиться"}