{"adjective": "небесно-голубой", "features": ["иметь хороший конец", "быть похожим на сказку"], "model": "google/gemma-2-27b-it bnb_4bit", "noun": "паук", "sha3_256": "41e298f8de29a78d699b4f1e8cde61e23a22cf1e3846deaccf0df911fcbae2f6", "story": "Жила-была маленькая девочка Маша. Она очень любила играть в саду. Однажды Маша увидела под листом большой, небесно-голубой паук. Паук сидел тихо и ковырял лапками свой домик.\n\nМаша очень удивилась. Она никогда не видела такого красивого паука! \"Привет, паук!\" - сказала Маша. Паук посмотрел на Машу своими большими глазами и помахал ей лапкой.\n\nМаша решила помочь пауку. Она принесла ему кусочек сочной ягоды. Паук съел ягоду и очень обрадовался. Он сплел для Маши маленький паутинный подарок - красивую звездочку.\n\nМаша была очень рада подарку. Она поблагодарила паука и побежала играть дальше. Паук остался сидеть под листом и ковырять свой домик, а Маша запомнила его как самого доброго паука на свете.", "verb": "ковырять"}