{"adjective": "ответственный", "features": ["иметь неожиданный поворот сюжета", "иметь двух персонажей", "быть поучительным", "плохо заканчиваться", "содержать диалог"], "model": "google/gemma-2-27b-it bnb_4bit", "noun": "овощ", "sha3_256": "460bdc83e3f1ee3e0bef276365d637904578ff00a996afcb8483476cb4800695", "story": "Маша очень не любила овощи.  \"Фу!\" - говорила она, когда мама ставила на стол тарелку с зелёным горошком. \"Я не хочу есть зелёные шарики!\"\n\nОднажды мама сказала: \"Маша, ты большая девочка, ты уже ответственная. Сегодня ты будешь помогать мне готовить ужин. Мы сделаем вкусный суп с овощами!\"\n\nМаша нахмурилась. \"Нет, я не хочу! Я не люблю овощи!\" Но мама сказала, что Маша должна быть ответственной, и Маша согласилась.\n\nМаша помогала маме чистить морковку и резать помидоры. Она даже попробовала маленький кусочек сырой морковки. \"Не так уж и плохо,\" подумала Маша.\n\nКогда суп был готов, Маша взяла большую ложку и... вылила весь суп в раковину! \"Я не хочу есть овощи!\" - закричала она. Мама была очень расстроена. Она сказала, что Маша не была ответственной и что теперь у них нет ужина.", "verb": "ненавидеть"}