{"adjective": "осторожный", "features": ["быть похожим на сказку", "содержать диалог", "иметь двух персонажей", "быть поучительным", "плохо заканчиваться"], "model": "google/gemma-2-27b-it bnb_4bit", "noun": "фрукт", "sha3_256": "47d0db3f2048095beef8e4cce21a938b90093bee5ee42b569522f9189b7ef6ee", "story": "Жила-была маленькая лисичка. Она очень любила фрукты. Яблоки, груши, ягоды – всё ей нравилось! Однажды лисичка увидела большой, сочный персик на ветке. \"Хочу этот персик!\" – подумала лисичка.\n\nОна стала одевать свою красную курточку, чтобы не замерзнуть. \"Ой, осторожно!\" – сказала лисичка себе. Она аккуратно залезла на ветку. Но ветка была тонкой и сломалась! Лисичка упала прямо на землю.\n\n\"Ой, больно!\" – заплакала лисичка. Она хотела взять персик, но он покатился далеко-далеко. Лисичка грустно посмотрела на персик. \"Теперь я не могу его съесть,\" – подумала она.\n\nЛисичка поняла, что нужно быть осторожной. Она решила больше не лазить на высокие ветки.", "verb": "одевать"}