{"adjective": "танцующий", "features": ["иметь двух персонажей", "иметь хороший конец", "иметь неожиданный поворот сюжета", "быть похожим на сказку", "содержать диалог", "быть поучительным"], "model": "google/gemma-2-27b-it bnb_4bit", "noun": "проблема", "sha3_256": "53f013e02954b6cc3b37c35eaddebcdf70ab75f249b8bfca12ff0a89c9c6bca2", "story": "Жила-была маленькая птичка по имени Чик. Чик очень любила щелкать клювом. Щелк-щелк, щелк-щелк! Она щелкала весь день, даже когда спала! Однажды Чик увидела большой, яркий цветок. \"Ой, проблема!\" - подумала Чик. \"Этот цветок такой красивый, но он закрыт! Как же мне его увидеть?\"\n\nЧик решила попробовать щелкать клювом на цветке. Щелк-щелк, щелк-щелк! Но цветок не открылся. Чик расстроилась. \"Что же делать?\" - спросила она у бабочки, которая сидела на листе рядом.\n\nБабочка улыбнулась. \"Чик, ты должна не щелкать, а танцевать!\" - сказала она. Чик удивилась. \"Танцевать? Но я не умею танцевать!\" Бабочка показала Чик, как кружиться и махать крыльями. Чик попробовала, и цветок медленно начал раскрываться!\n\nЧик была очень рада. Она поняла, что не всегда нужно щелкать, чтобы решить проблему. Иногда нужно попробовать что-то новое, например, танцевать! Чик и бабочка стали танцевать вместе, и цветок распустился полностью, показывая свои яркие лепестки.", "verb": "щелкать"}