{"adjective": "плавающий", "features": ["быть похожим на сказку", "плохо заканчиваться"], "model": "google/gemma-2-27b-it bnb_4bit", "noun": "скорость", "sha3_256": "588f0d7195830d0ca2d38d6dedc5bab675cf6cb4f66e63a28e69c53b3b1cc489", "story": "Жила-была маленькая рыбка. Она была очень красивой, с синими чешуйками и плавающим хвостом. Рыбка любила плавать очень быстро, ее скорость была просто невероятной! Она могла проплыть весь пруд за одну минуту.\n\nОднажды рыбка решила поплыть еще быстрее, чем обычно. Она плыла и плыла, а потом вдруг... исчезла! Ее синие чешуйки больше не блестели на солнце, а плавающий хвост перестал двигаться.\n\nДругая рыбка, которая плыла рядом, очень испугалась. \"Где же наша подруга?\" - спросила она. Но никто не знал ответа. Рыбка исчезла так быстро, что никто не успел ее увидеть.\n\nТеперь в пруду стало очень грустно. Все рыбки скучали по своей быстрой подруге. Они плавали по всему пруду, надеясь ее найти, но рыбка так и не появилась.", "verb": "исчезать"}