{"adjective": "особенный", "features": ["иметь трёх персонажей", "иметь хороший конец", "быть поучительным"], "model": "google/gemma-2-27b-it bnb_4bit", "noun": "уточка", "sha3_256": "6142b5e1a852ab30f0cf2e60afcd869d050bfdc2d6925ba4ce2196fd2f59ae78", "story": "Жила-была маленькая уточка. Она была очень особенная, потому что у неё было жёлтое перышко на голове. Уточка любила играть с двумя своими друзьями: зайчиком и лисенком.\n\nОднажды, уточка увидела большой, большой шар. Она хотела поиграть с ним, но шар был очень тяжёлый. Уточка пыталась его подтолкнуть, но он не двигался. Она пыталась его клювом сдвинуть, но он всё равно оставался на месте. Уточка расстроилась, её маленькое сердце сжималось от грусти.\n\nЗайчик и лисёнок увидели, что уточка грустная. Они подошли к ней и спросили, что случилось. Уточка рассказала им про большой шар. Зайчик и лисёнок решили помочь. Они стали толкать шар вместе, и он медленно, медленно начал двигаться.\n\nУточка была очень рада! Она поняла, что если друзья помогают друг другу, то даже самые тяжёлые задачи можно решить.  Все вместе они весело играли с большим шаром до самого вечера.", "verb": "сжиматься"}