{"adjective": "небесно-голубой", "features": ["иметь хороший конец", "иметь одного персонажа", "быть поучительным"], "model": "google/gemma-2-27b-it bnb_4bit", "noun": "утро", "sha3_256": "686ddf73b5081abb0cdab44f21dc63c151732640d0af7bad820291136459ef58", "story": "Маленький зайчик проснулся утром. Солнце светило ярко, небо было небесно-голубое. Зайчик хотел поиграть, но его ушки были грустные. Они изгибались вниз, как будто хотели спать.\n\nЗайчик подумал: \"Почему мои ушки грустные?\" Он посмотрел на солнце, на небо, на цветы. Все было так красиво! Зайчик понял, что его ушки грустят, потому что он не рад.\n\nЗайчик решил быть счастливым. Он прыгнул, закружился, и его ушки стали прямыми и веселыми! Они изгибались вверх, как будто хотели дотронуться до солнца.\n\nЗайчик понял, что счастье зависит от нас самих. Если мы хотим быть счастливыми, нужно улыбаться и радоваться жизни! \n\nС этого дня зайчик всегда старался быть счастливым, и его ушки были всегда прямыми и веселыми.", "verb": "изгибаться"}