{"adjective": "весёлый", "features": ["быть похожим на сказку", "содержать диалог", "иметь двух персонажей", "иметь неожиданный поворот сюжета"], "model": "google/gemma-2-27b-it bnb_4bit", "noun": "пантера", "sha3_256": "6bb2c23ee0f3d6acfcd5535137df04bb064945f3cb292e7adab5f40cc69969f3", "story": "Жила-была маленькая пантера. Она была очень весёлая и любила играть. Однажды, пантера нашла много красивых кубиков. \"Ура!\" - закричала пантера. \"Теперь я буду складывать из них большой дом!\"\n\nПантера начала складывать кубики. Один, два, три... Она старалась сделать свой дом высоким и красивым. \"Какой замечательный дом у меня получится!\" - подумала пантера.\n\nВдруг, из-за куста выскочил маленький зайчик. \"Привет, пантера!\" - сказал зайчик. \"Что ты делаешь?\" Пантера показала зайчику свой дом из кубиков. \"Я хочу жить в этом доме!\" - сказал зайчик.\n\nПантера улыбнулась. \"Конечно, зайчик, ты можешь жить в моем доме!\"  Она была очень рада, что нашла нового друга.\n\nНо тут зайчик хитро улыбнулся. \"Спасибо, пантера!\" - сказал он. И, быстро подхватив все кубики, убежал! Пантера удивилась. \"Что же теперь делать?\" - подумала она. Но пантера не расстроилась. Она знала, что найдет новые кубики и построит еще более красивый дом!", "verb": "складывать"}