{"adjective": "бодрый", "features": ["содержать диалог", "иметь неожиданный поворот сюжета", "быть поучительным"], "model": "google/gemma-2-27b-it bnb_4bit", "noun": "дракон", "sha3_256": "6c124bb8ea8bf0e1209b3fcd2c05b7c078f9ec5d52506c676139a5b7e393f4db", "story": "Маша играла с мишкой. Мишка был очень мягкий и пушистый. Маша любила его обнимать.\n\n— Пойдем гулять, мишка? — спросила Маша. Мишка молчал, потому что он был игрушкой. Но Маша всё равно думала, что он соглашается.\n\nВдруг Маша увидела большого дракона! Он был зелёный, с большими крыльями и острыми зубами. Маша испугалась.\n\n— Ты хочешь гулять? — спросил дракон. Маша кивнула. Дракон был очень бодрый и предложил Маше покататься на спине. Маша согласилась и села на дракона.\n\nОни полетели высоко в небо! Маша увидела всё вокруг: деревья, дома, речку. Дракон был очень добрый и аккуратно посадил Машу обратно на землю. Маша поняла, что не нужно бояться новых друзей, даже если они выглядят страшными.", "verb": "соглашаться"}