{"adjective": "особенный", "features": ["содержать диалог", "иметь двух персонажей", "быть похожим на сказку"], "model": "google/gemma-2-27b-it bnb_4bit", "noun": "аттракцион", "sha3_256": "70b1574d50bde704cef5836c5ecb8731ceae439bffa2695bc08988c3a7dd9534", "story": "В солнечном лесу жила маленькая белочка по имени Лисичка. Она любила бегать по деревьям, собирать орешки и играть с солнцем. Однажды, Лисичка услышала веселый смех и увидела яркий аттракцион. Он был особенный! Карусель с разноцветными зверями крутилась и крутилась, а на ней сидели счастливые дети.\n\nЛисичка хотела покататься, но боялась. Она подошла к милой девочке, которая сидела на скамейке. \"Приветствовать тебя, девочка!\" - сказала Лисичка. \"Что это за аттракцион? Можно мне покататься?\"\n\nДевочка улыбнулась. \"Привет, Лисичка! Это карусель! Она крутится и крутится, очень весело! Хочешь покататься? Я помогу тебе!\"\n\nЛисичка была очень рада. Девочка помогла ей забраться на карусель, и Лисичка поехала вместе с другими зверями. Она смеялась и радовалась, потому что карусель была очень особенной!", "verb": "приветствовать"}