{"adjective": "ужасный", "features": ["быть похожим на сказку", "иметь двух персонажей", "иметь хороший конец", "иметь неожиданный поворот сюжета"], "model": "google/gemma-2-27b-it bnb_4bit", "noun": "желание", "sha3_256": "7351720540edd97e1fb5db021c7f48af02c8ed5b8f893c74aaa1a36b4bba5c17", "story": "Жила-была маленькая девочка Маша. Маша очень любила играть в куклы. У неё была кукла Катя, с которой она никогда не расставалась. Однажды Маша решила одевать Катю в красивое красное платье. Но платье было ужасно грязным! Маша расстроилась, потому что очень хотела одевать Катю в это платье.\n\nВдруг, Маша увидела маленькую птичку, которая сидела на подоконнике. Птичка чирикала и смотрела на Машу своими большими чёрными глазками. Маша поняла, что птичка хочет помочь ей. Она взяла Катю и показала её птичке. Птичка взмахнула крыльями и полетела к окну.\n\nМаша удивилась! Птичка принесла в клюве маленькую веточку. Веточка была очень мягкая и пушистая. Маша поняла, что птичка хочет, чтобы она почистила платье веточкой. Маша аккуратно почистила платье, и оно стало чистым и красивым!\n\nМаша очень обрадовалась. Она одевала Катю в красное платье и играла с ней весь день. Маша поняла, что даже маленькая птичка может помочь, если у неё есть желание. \n\nС тех пор Маша всегда помогала птичкам, а они помогали ей.", "verb": "одевать"}