{"adjective": "песочный", "features": ["быть похожим на сказку", "плохо заканчиваться", "иметь трёх персонажей", "содержать диалог", "иметь неожиданный поворот сюжета"], "model": "google/gemma-2-27b-it bnb_4bit", "noun": "ревность", "sha3_256": "80526972775a58bb065bd52f975fea96016782e54ae5b0eaa821c1a12dfb1dad", "story": "Жила-была маленькая мишка. Она любила играть в песочнице. Однажды мишка увидела, как птичка взбирается на высокую гору из песка. \"Хочу тоже туда!\" - подумала мишка.\n\nМишка начала взбираться на гору. Вдруг к ней подбежала лисичка. \"Это моя гора!\" - сказала лисичка. \"Я хочу играть здесь!\" - ответила мишка. Лисичка посмотрела на мишку с ревностью. \"Нет, это моя гора!\" - снова закричала лисичка.\n\nМишка расстроилась. Она хотела играть, но лисичка не давала. Вдруг, из песка вылез большой, страшный дракон! Он был очень сердитый и хотел съесть мишку и лисичку!\n\nМишка и лисичка испугались и побежали. Дракон за ними гнался. Они бежали и бежали, пока не оказались далеко от песочной горы. Мишка и лисичка больше никогда не хотели играть на этой горе.", "verb": "взбираться"}