{"adjective": "ледяной", "features": ["быть похожим на сказку", "иметь трёх персонажей", "иметь неожиданный поворот сюжета", "содержать диалог", "плохо заканчиваться"], "model": "google/gemma-2-27b-it bnb_4bit", "noun": "луна", "sha3_256": "809604fc2d587ccca2a81be504298ac5a32ee2ddda6d73c90256a1facfeb185e", "story": "Жила-была маленькая девочка Лиза. Она любила смотреть на небо. Однажды вечером Лиза увидела большую, светлую луну.\n\n\"Смотри, смотри!\" - закричала Лиза. \"Луна указывает на лес!\"\n\nРядом с Лизой стояли ее друзья - мишка и зайчик.\n\n\"Что там в лесу?\" - спросил мишка, боясь идти туда.\n\n\"Там ледяной торт!\" - ответила Лиза. \"Луна показывает нам дорогу!\"\n\nЛиза побежала в лес, мишка и зайчик побежали за ней. Но в лесу было темно и страшно. Лиза споткнулась и упала.\n\n\"Ой!\" - закричала Лиза.\n\nМишка и зайчик испугались и убежали. Лиза осталась одна в темном лесу. Луна все еще светила, но Лиза больше не хотела идти к ледяному торту. Она хотела домой.", "verb": "указывать"}