{"adjective": "больной", "features": ["иметь неожиданный поворот сюжета", "иметь трёх персонажей"], "model": "google/gemma-2-27b-it bnb_4bit", "noun": "корова", "sha3_256": "82b7a9431827cbe4e9f66621ac06d3d5ec2837d7db46888e9567693744f565e0", "story": "Жила-была корова Муся. Она была большая и рыжая, с большими глазами и мягким носом. Муся очень любила клевать травку на лугу. \n\nОднажды Муся почувствовала себя плохо. Она стала вялая, не хотела клевать травку и часто кашляла. Друзья Муси, зайчик Пушистик и птичка Чик-чирик, очень волновались.\n\n\"Муся, что с тобой?\" - спрашивал Пушистик, трогая ее носом. \"Ты больна?\" Чик-чирик кружил над Мусей, чирикал тревожно.\n\nМуся только вздыхала. \"Я не знаю, что со мной,\" - говорила она. \"Мне плохо\".\n\nВдруг Чик-чирик закричал: \"Смотри, Муся, что это?\" Он махал крыльями и указывал на что-то в траве. Пушистик и Муся посмотрели и увидели... маленького котенка! Он был совсем крошечный, с синими глазами и пушистым хвостом.\n\n\"Он потерялся!\" - воскликнула Муся. \"Нам нужно его найти маме!\"\n\nИ Муся, забыв о своей болезни, встала и пошла искать маму котенка. Пушистик и Чик-чирик побежали за ней.", "verb": "клевать"}