{"adjective": "неуклюжий", "features": ["быть похожим на сказку", "иметь хороший конец", "быть поучительным", "содержать диалог", "иметь неожиданный поворот сюжета"], "model": "google/gemma-2-27b-it bnb_4bit", "noun": "тишина", "sha3_256": "85fe235a46795fb15388ed41091c0ab40ff2fd941807dcae274ca33cf7a282a0", "story": "Жила-была маленькая птичка. Она была очень неуклюжая. Всегда спотыкалась о ветки и падала с веток. Однажды, сидя на ветке, птичка услышала тишину. Никто не пел, не шумел, не журчал ручей.\n\n\"Где все?\" - спросила птичка у совы, которая сидела на соседней ветке.\n\n\"Все спрятались,\" - ответила сова. \"Злой волк пришел в лес. Он хочет съесть всех!\"\n\nПтичка испугалась. Она хотела спрятаться, но не знала, куда. Вдруг, она увидела ручей, который журчал совсем тихо. Птичка прыгнула в воду и спряталась под листиками.\n\nВолк пришел, посмотрел на пустой лес и ушел. Птичка вышла из воды, вся мокрая, но счастливая. Она поняла, что даже неуклюжая птичка может быть храброй!\n\nС тех пор, птичка больше не боялась. Она знала, что даже в тишине, когда все спрятались, всегда есть выход.", "verb": "журчать"}