{"adjective": "аккуратный", "features": ["быть поучительным", "быть похожим на сказку", "плохо заканчиваться", "иметь неожиданный поворот сюжета"], "model": "google/gemma-2-27b-it bnb_4bit", "noun": "коридор", "sha3_256": "8b076670a9d75733a1f1273de1d5afa32f43398c92780210f89b704b8d25b7c2", "story": "Жила-была маленькая девочка Маша. Маша любила играть с куклами. Однажды, Маша играла в коридоре. Она строила домик из подушек для своей любимой куклы. Мама сказала: \"Маша, убирай игрушки, когда закончишь играть\". Маша кивнула головой, соглашаясь.\n\nМаша играла долго. Она сделала для куклы аккуратную кроватку из коробки и повесила на стену красивую картинку. Маша устала и решила отдохнуть. Она забыла про обещание маме.\n\nВдруг, в коридор вошел большой серый волк! Он увидел куклу Маши и решил ее съесть! Маша испугалась и спряталась за диван. Волчок быстро схватил куклу и убежал.\n\nМаша заплакала. Она очень любила свою куклу. Мама пришла и увидела, что Маша плачет. Маша рассказала про волка. Мама обняла Машу и сказала: \"Если бы ты убрала игрушки, волк не нашел бы твою куклу\".", "verb": "соглашаться"}