{"adjective": "светло-красный", "features": ["быть поучительным", "быть похожим на сказку", "иметь хороший конец", "содержать диалог"], "model": "google/gemma-2-27b-it bnb_4bit", "noun": "принцесса", "sha3_256": "8b5fe3c8f5d04b17130564c12ff647af499b708b15bc07b1e0a7f1e4f62cc2b6", "story": "Жила-была принцесса. У неё было красивое платье, светло-красное, как солнышко! Принцесса любила кататься на лошадке. Лошадка везла её по лесу, по полям, по всему королевству.\n\nОднажды принцесса решила поехать в лес. Она села на лошадку и сказала: \"Вези меня, лошадка, в лес!\". Лошадка послушно побежала по тропинке. В лесу принцесса увидела маленького зайчика. Зайчик плакал.\n\n\"Что случилось, зайчик?\" - спросила принцесса. \"Я потерял маму,\" - ответил зайчик. Принцесса решила помочь. Она велела лошадке везти её по лесу, пока они не найдут маму зайчика.\n\nЛошадка везла принцессу по лесу, пока не услышали тихий писк. Зайчик радостно побежал к маме. Мама зайчика была очень рада. Принцесса была счастлива, что помогла. Она поняла, что важно помогать другим, даже если это зайчик, потерявший маму.\n\nЛошадка везла принцессу домой, а принцесса думала о том, как хорошо делать добрые дела.", "verb": "везти"}