{"adjective": "реалистичный", "features": ["содержать диалог", "иметь двух персонажей", "плохо заканчиваться"], "model": "google/gemma-2-27b-it bnb_4bit", "noun": "львица", "sha3_256": "9163fa26b27e3df8fcde15225cea7c846b0a82061b89e4d9cc49172251c8b384", "story": "Маша и Миша играли на полу. У них были цветные листы бумаги и клей.\n\n\"Давай сделаем львицу!\" - сказала Маша. Она взяла жёлтый лист и начала клеить его на другой лист, чтобы получился круг.\n\n\"Львица будет рыжая!\" - сказал Миша. Он взял оранжевый лист и начал клеить его поверх жёлтого.\n\n\"Нет, львицы жёлтые!\" - возразила Маша. Она хотела сделать свою львицу самой реалистичной.\n\nМиша рассердился. \"Моя львица будет рыжей!\" - закричал он и начал рвать бумагу. Маша заплакала. Их львица так и не получилась.", "verb": "клеить"}