{"adjective": "креативный", "features": ["иметь трёх персонажей", "содержать диалог", "быть похожим на сказку", "иметь хороший конец"], "model": "google/gemma-2-27b-it bnb_4bit", "noun": "глина", "sha3_256": "93d03941f8cf23c779e0f94cbb644e9b59502e5382f860cef5fc3eb05599ce04", "story": "Жила-была девочка Маша. У Маши был друг, мишка Тоша, и еще одна подруга, птичка Чик-чирик. Однажды Маша играла с глиной. Она лепила из нее разные фигурки: зайчика, солнышко, даже домик!\n\n\"Смотри, Тоша, что я слепила!\" - сказала Маша, показывая мишке глиняный домик. \"А я хочу слепить что-то другое!\" - ответил Тоша. Он взял глину и начал совать ее в свой рот. \"Нет, Тоша, так нельзя!\" - закричала Маша. \"Глина не для еды!\"\n\nЧик-чирик, сидя на ветке, весело чирикал. \"Я знаю, как сделать из глины что-то интересное!\" - сказала она. Чик-чирик совала лапки в глину и делала отпечатки. \"Вот, смотри, Маша, птички!\"\n\nМаша и Тоша были очень рады. \"Какая ты креативная, Чик-чирик!\" - сказала Маша. \"Теперь у нас есть глиняные птички!\" - обрадовался Тоша. Все вместе они играли с глиной до вечера, создавая новые и интересные фигурки.", "verb": "совать"}