{"adjective": "непрозрачный", "features": ["плохо заканчиваться", "иметь двух персонажей", "быть похожим на сказку", "иметь неожиданный поворот сюжета"], "model": "google/gemma-2-27b-it bnb_4bit", "noun": "сон", "sha3_256": "93d39f2e57736df67b3817ea4bdf1de942742a80cdd104433c05c0eed62f94f0", "story": "Жила-была маленькая девочка Лиза. Она любила играть с солнышком. Лиза бегала по лужайке, а солнышко грело ее спинку. Лиза смеялась, а солнышко светило ярче.\n\nОднажды Лиза увидела, что солнышко стало желтеть. Оно не было таким ярким, как обычно. Лиза испугалась. Она побежала домой и рассказала маме про желтое солнышко.\n\nМама взяла Лизу за руку и сказала: \"Не бойся, солнышко просто хочет спать\". Она повела Лизу в спальню и уложила ее спать. \"Солнышко спит, а мы тоже будем спать\", - сказала мама.\n\nЛиза закрыла глаза, но не могла уснуть. Она думала о желтом солнышке. Вдруг Лиза увидела, что ее комната наполнена непрозрачным туманом. Из тумана вылезло маленькое солнышко, но оно было не желтое, а синее!\n\n\"Я не хочу спать!\", - прокричало синее солнышко. Лиза испугалась и спряталась под одеяло. Что будет дальше, никто не знает...", "verb": "желтеть"}