{"adjective": "вымышленный", "features": ["иметь одного персонажа", "быть поучительным", "иметь неожиданный поворот сюжета", "плохо заканчиваться"], "model": "google/gemma-2-27b-it bnb_4bit", "noun": "ощущение", "sha3_256": "9d5ba58a8c4f622cbac095d899bcaa66c53ef896c55edc80f982b297158e4af6", "story": "Миша любил играть. Он играл с машинками, с кубиками, с мячиком. Но больше всего Миша любил играть в вымышленный мир. Он представлял себя сильным рыцарем, который сражается с драконами.\n\nМиша очень старался. Он работал своими руками, строил из кубиков замки, из одеял делал драконов. Он хотел, чтобы его мир был настоящим! Миша хотел почувствовать, как дракон дышит огнем, как меч бьется о щит.\n\nОднажды Миша решил построить самый большой дракон. Он взял все одеяла, все подушки, все мягкие игрушки. Он работал долго, очень долго. Наконец, дракон был готов! Он был огромный, страшный и очень пушистый.\n\nМиша хотел потрогать дракона, почувствовать его мягкую шерсть. Но когда он коснулся одеяла, оно упало, и Миша оказался под ним. Миша пытался выбраться, но одеяло было слишком тяжелым. Миша кричал, но никто его не слышал.\n\nМиша понял, что его вымышленный мир стал опасным. Он хотел играть, но теперь он хотел выбраться из-под одеяла.", "verb": "работать"}