{"adjective": "охотящийся", "features": ["иметь одного персонажа", "плохо заканчиваться"], "model": "google/gemma-2-27b-it bnb_4bit", "noun": "перец", "sha3_256": "a40e006422a9a3ee62d1b2b22b5b69bb0df461b5da548215cbe14dc621edff62", "story": "Маша гуляла по саду. Солнце светило ярко, и Маша улыбалась. Она увидела красный перец на кусте. Он был большой и красивый! Маша хотела его сорвать, но перец сидел высоко.\n\nМаша стала прыгать. Она прыгала и прыгала, но перец был всё так же высоко. Маша вздохнула. Вдруг, из-за куста выскочил большой, охотящийся кот! Он посмотрел на Машу, а потом на перец.\n\nКот хотел съесть перец! Маша испугалась и побежала. Кот побежал за ней. Маша бежала быстро, но кот был быстрее.\n\nМаша упала и заплакала. Кот подошёл к перцу и начал его распускать. Маша хотела помочь перцу, но кот был слишком страшный.", "verb": "распускать"}