{"adjective": "безопасный", "features": ["иметь неожиданный поворот сюжета"], "model": "google/gemma-2-27b-it bnb_4bit", "noun": "капуста", "sha3_256": "aaaed6581406cbbe03597fefb3480fa797d3e12407e90bc8c6f6febfea1864b6", "story": "Маша и Миша играли в саду. Солнце светило ярко, птички пели весело. Маша веселилась, бегала по траве и смеялась. Миша нашел большую капусту. Она была зеленая и круглая, как мячик.\n\nМиша решил покататься на капусте, как на лошадке. Он сел на нее и стал толкать ногами. Капуста покатилась по траве, Миша веселился! Маша тоже захотела покататься.\n\nВдруг, капуста остановилась! Миша увидел, что капуста не просто капуста, а маленький домик! Дверь в домике была открыта. Миша заглянул внутрь. Там сидел маленький зайчик.\n\n\"Привет!\" - сказал зайчик. \"Я живу в этом домике. Хотите поиграть со мной?\" Миша и Маша обрадовались. Они вошли в домик и стали играть с зайчиком.\n\nЭто был самый безопасный и веселый день!", "verb": "веселиться"}