{"adjective": "пухлый", "features": ["иметь хороший конец", "иметь трёх персонажей", "иметь неожиданный поворот сюжета", "быть похожим на сказку"], "model": "google/gemma-2-27b-it bnb_4bit", "noun": "лебедь", "sha3_256": "b2d148f51a3a3e56c041d1314ade5f0c4b3b5af1e1655f2ee2b47c20bcaabc2e", "story": "Жила-была маленькая девочка Маша. Она любила гулять по лесу и смотреть на птиц. Однажды Маша увидела пухлого лебедя. Он сидел на берегу озера и грустно смотрел на воду.\n\n\"Бедняжка,\" подумала Маша. \"Он, наверное, жалеет, что не может плавать.\" Маша хотела помочь лебедю. Она взяла ведро и набрала воды.\n\n\"Вот, лебедь, пей!\" сказала Маша. Лебедь посмотрел на Машу, потом на ведро, и вдруг расхохотался!\n\n\"Я не жалею, что не могу плавать!\" крикнул лебедь. \"Я просто очень люблю сидеть на берегу и смотреть на рыбок!\" Маша удивилась. Она никогда не думала, что лебедь может так смеяться!\n\nМаша и лебедь стали друзьями. Они играли вместе на берегу озера, и Маша больше не жалела лебедя.", "verb": "жалеть"}