{"adjective": "синий", "features": ["иметь трёх персонажей", "содержать диалог", "быть поучительным"], "model": "google/gemma-2-27b-it bnb_4bit", "noun": "пекарь", "sha3_256": "b30e9ee5ab663bb60931c4f63c3569066efe8dd78fe5f5bedca91b3fda6faa1e", "story": "Маша, Коля и их мама шли по улице. Мама шла быстро, а Маша с Колей бегали вокруг нее.\n\n\"Ой, как вкусно пахнет!\" - сказала Маша, остановившись.\n\n\"Да, пахнет хлебом!\" - ответил Коля.\n\nОни увидели маленькую пекарню. Из нее шел ароматный запах свежего хлеба. В пекарне стоял пекарь в белой шапочке.\n\n\"Здравствуйте!\" - поздоровалась мама. \"Ваш хлеб так вкусно пахнет!\"\n\nПекарь улыбнулся. \"Спасибо! У меня есть свежий хлеб с синими ягодами. Хотите попробовать?\"\n\nМама купила хлеб. Маша и Коля попробовали его. \"Вкусно!\" - сказали они.\n\n\"Важно всегда быть добрыми, как пекарь,\" - сказала мама. \"Он поделился своим вкусным хлебом с нами.\"", "verb": "пахнуть"}