{"adjective": "неправильный", "features": ["содержать диалог", "быть похожим на сказку", "быть поучительным", "плохо заканчиваться", "иметь двух персонажей"], "model": "google/gemma-2-27b-it bnb_4bit", "noun": "корова", "sha3_256": "b63739c6e84071b2ad767c9b90e0c537ffefc700ef5a0464e5481f77db1fa102", "story": "Жила-была корова Мука. Она была большая и белая, с чёрными пятнами. Мука любила есть траву и играть с птицами. Однажды, Мука увидела маленького зайчика. Зайчик плакал.\n\n\"Что случилось?\" - спросила Мука.\n\n\"Я хочу есть, но не могу найти траву!\" - ответил зайчик.\n\nМука решила помочь. Она взяла зайчика на спину и пошла искать траву. Но Мука забыла, что зайчики едят только маленькую траву, а она нашла только большую.\n\n\"Это неправильная трава!\" - сказал зайчик. \"Я не могу её есть!\"\n\nМука расстроилась. Она хотела помочь зайчику, но не знала, как. Зайчик остался голодным, а Мука грустила.", "verb": "кормить"}