{"adjective": "чирикающий", "features": ["быть поучительным", "иметь двух персонажей", "иметь хороший конец", "быть похожим на сказку"], "model": "google/gemma-2-27b-it bnb_4bit", "noun": "друг", "sha3_256": "b9fdce55a29be017b9a92f872fb7ce1a707b9ca54b740670f993e617422d325b", "story": "Жила-была маленькая птичка. Она была очень чирикающая, всегда пела веселые песенки. Однажды птичка увидела большого, сильного медведя. Медведь плакал.\n\n\"Почему ты плачешь?\" - спросила птичка.\n\n\"Я потерял своего друга,\" - ответил медведь грустно. \"Мы играли, а потом я не увидел его.\"\n\nПтичка подумала немного. \"Не бойся,\" - сказала она. \"Я помогу тебе найти друга!\"\n\nПтичка полетела высоко в небо и стала чирикать очень громко. Ее чириканье было так весело, что друг медведя услышал его и побежал к ним. Медведь был очень рад! Он обнял своего друга и сказал птичке \"спасибо\". \n\nПтичка была счастлива, что помогла. Она поняла, что даже маленькая птичка может сделать что-то хорошее.", "verb": "плакать"}