{"adjective": "бесчувственный", "features": ["иметь двух персонажей", "быть поучительным", "иметь хороший конец"], "model": "google/gemma-2-27b-it bnb_4bit", "noun": "ревность", "sha3_256": "bf980e848733788de762340a60f0741f1c1dccf0c780957bd41080f532d8e4e7", "story": "Жила-была милая собачка по имени Тузик. Тузик очень любил играть с мячиком. Однажды, к Тузику в гости приехал большой кот Васька. Васька тоже хотел играть с мячиком. Тузик начал рычать, потому что не хотел делиться. Он был ревнивым и хотел играть только сам.\n\nВаська грустно посмотрел на Тузика. \"Почему ты рычишь?\" - спросил он. \"Я тоже хочу играть!\" Тузик посмотрел на Ваську и понял, что кот просто хочет веселиться. Тузик почувствовал себя немного стыдно. Он был бесчувственным, когда рычал.\n\nТузик решил поделиться мячиком с Васькой. Они стали играть вместе, и им было очень весело! Тузик понял, что делиться с друзьями - это хорошо. Теперь у Тузика и Васьки было много друзей, потому что они всегда делились своими игрушками.", "verb": "рычать"}