{"adjective": "короткий", "features": ["плохо заканчиваться"], "model": "google/gemma-2-27b-it bnb_4bit", "noun": "львёнок", "sha3_256": "c974c0055777dc0b6b05302bc5ed624cfb58e50033aaf8291d5f8e1732c98a14", "story": "Мама читала сказку про львёнка. Львёнок был маленький и пушистый. У него был короткий хвостик. Мама говорила, что львёнок очень любил играть.\n\nЛьвёнок играл с мячиком. Он бегал и прыгал. Потом он увидел бабочку. Бабочка была красивая, с яркими крылышками. Львёнок хотел поймать бабочку.\n\nЛьвёнок побежал за бабочкой. Он бежал очень быстро. Бабочка летела высоко. Львёнок не мог ее догнать.\n\nМама закрыла книгу. Львёнок остался один. Он вспоминал про бабочку. Он хотел поиграть с ней. Но бабочки уже не было. \n\nЛьвёнок грустил. Он хотел найти бабочку, но не знал, где ее искать.", "verb": "вспоминать"}