{"adjective": "говорящий", "features": ["плохо заканчиваться", "иметь двух персонажей"], "model": "google/gemma-2-27b-it bnb_4bit", "noun": "еда", "sha3_256": "cd4c8ba14212317dfd091dda36fb9a5bd85ceaec866657e18cfa7e146e480ebf", "story": "Маша и Миша играли в домик. Маша взяла большой ящик и стала его разворачивать. В ящике была вкусная еда: яблоки, печенье и конфеты!\n\nМиша увидел еду и обрадовался. \"Ура! Еда!\" - закричал он.\n\nВдруг из ящика вылез говорящий кот! \"Мяу! Я хочу есть!\" - сказал кот.\n\nМаша и Миша испугались. Говорящий кот посмотрел на еду и начал быстро ее есть.\n\nМаша и Миша хотели взять еду, но кот съел все! \"Ой, нет!\" - заплакала Маша.", "verb": "разворачивать"}