{"adjective": "редкий", "features": ["быть похожим на сказку", "иметь двух персонажей", "содержать диалог", "иметь хороший конец", "иметь неожиданный поворот сюжета"], "model": "google/gemma-2-27b-it bnb_4bit", "noun": "каток", "sha3_256": "d1e8c284daa9f5b08b8dc420004449e750438538811855cab79f846f99b9fad6", "story": "Жила-была маленькая лисичка. Она очень любила кататься на катке. Лед был гладкий, как зеркало, и лисичка могла быстро бегать по нему. Однажды лисичка увидела на катке редкого белого зайчика. Зайчик был очень красивым, с длинными ушками и пушистым хвостом.\n\nЛисичка хотела познакомиться с зайчиком, но очень краснела, когда он смотрел на неё своими большими чёрными глазами. \"Привет,\" - тихо сказала лисичка. \"Хочешь покататься со мной?\" Зайчик улыбнулся и кивнул.\n\nОни стали кататься вместе, лисичка учила зайчика делать круги, а зайчик показывал лисичке, как прыгать на льду. Они играли и смеялись, пока не устали.\n\nВдруг, зайчик остановился и сказал: \"Лисичка, я не настоящий зайчик! Я - волшебный снеговик! Лед растает, и я превращусь в обычный снег!\" Лисичка удивилась, но не испугалась. Она обняла снеговика и сказала: \"Спасибо за игру! Я очень рада, что познакомилась с тобой!\"\n\nСнеговик рассмеялся и сказал: \"Я тоже! А теперь беги домой, пока не стало совсем тепло!\" Лисичка побежала домой, а снеговик растаял, оставив на льду только маленькую кучку снега.", "verb": "краснеть"}