{"adjective": "зелёный", "features": ["иметь трёх персонажей", "быть похожим на сказку", "плохо заканчиваться", "иметь неожиданный поворот сюжета"], "model": "google/gemma-2-27b-it bnb_4bit", "noun": "врач", "sha3_256": "de40fadf5222c708ffe034ceb0e4106f258212efec87fde3e7997ece7a191e73", "story": "Жила-была маленькая девочка Маша. У Маши был милый щенок, который любил играть в грязи. Однажды щенок так сильно испачкался, что стал совсем коричневым! Маша решила постирать его в речке.\n\nВ речке плавала добрая рыбка. Она увидела Машу и спросила: \"Что ты делаешь?\" Маша ответила: \"Я стираю своего щенка, он очень грязный!\" Рыбка сказала: \"Я могу помочь тебе! Я знаю волшебное зелье, которое сделает твоего щенка чистым!\"\n\nРыбка дала Маше зелёное зелье. Маша налила его на щенка, и он стал не просто чистым, а зелёным! Маша обрадовалась, но щенок вдруг начал расти, расти и расти! Он стал огромным, как дом!\n\nМаша испугалась и побежала к врачу. Врач посмотрел на зелёного щенка и сказал: \"Это не обычный щенок! Нужно срочно найти рыбку и попросить её снять волшебство!\" Маша побежала к речке, но рыбки там уже не было. \n\nМаша осталась одна с огромным зелёным щенком.", "verb": "стирать"}