{"adjective": "холодный", "features": ["иметь одного персонажа", "быть похожим на сказку", "иметь хороший конец"], "model": "google/gemma-2-27b-it bnb_4bit", "noun": "молоко", "sha3_256": "df69e4449fb91a099c8fcfcc95d45833fc01f1ab080501ba3b3af7b96204b867", "story": "Жила-была маленькая зайчиха. Она очень любила молоко.  Каждое утро зайчиха пила холодное молоко и мечтала о том, как будет прыгать по лугу.\n\nОднажды зайчиха проснулась и увидела, что ее миска с молоком пуста! Она очень расстроилась. \"Где же мое молоко?\" - подумала зайчиха.\n\nВдруг зайчиха увидела на столе маленькую бутылочку. Она открыла ее и увидела, что там тоже холодное молоко! Зайчиха выпила все молоко и почувствовала себя очень счастливой.\n\nТеперь зайчиха могла прыгать по лугу! Она прыгала и прыгала, пока не устала. А потом она легла спать, думая о том, как хорошо быть зайчиком.", "verb": "мечтать"}