{"adjective": "небесно-голубой", "features": ["иметь хороший конец", "иметь трёх персонажей", "быть поучительным"], "model": "google/gemma-2-27b-it bnb_4bit", "noun": "сом", "sha3_256": "e23ee11423e850f7a42e501ca2b6120fe95a9dc8a6f6e47c61b9a737ebd548df", "story": "Маша, Коля и их щенок Дружок играли в саду. Солнце светило ярко, небо было небесно-голубое. Маша спрятала свой любимый красный мячик под большой листвой.\n\n\"Где мячик?\" - спросил Коля. Дружок вилял хвостом, пытаясь помочь. Маша показала на листву. \"Он там!\"\n\nДружок, увидев листву, залаял радостно и начал рыть землю. \"Нет, Дружок, не надо рыть!\" - сказала Маша. \"Мячик просто спрятан под листвой\".\n\nКоля аккуратно отодвинул листву, и они увидели мячик. \"Ура!\" - закричали дети. Дружок радостно прыгал вокруг них.\n\nМаша поняла, что прятать вещи нужно аккуратно, чтобы их было легко найти. А Дружок понял, что рыть землю не всегда нужно, когда что-то спрятано.", "verb": "прятать"}