{"adjective": "длинный", "features": ["иметь хороший конец", "содержать диалог", "иметь неожиданный поворот сюжета", "быть поучительным"], "model": "google/gemma-2-27b-it bnb_4bit", "noun": "кресло", "sha3_256": "e892f1cc4c2551fbf90bd53668ba8e2d15c71eeaf5c051c706a988cfcce10a8d", "story": "Маша играла с мишкой. Мишка сидел на длинном кресле. Маша хотела поиграть с мишкой на полу. Она дергала мишку за лапу. \"Иди сюда, мишка!\" - сказала Маша.\n\nНо мишка не шел. Он сидел крепко на кресле. Маша дергала и дергала, но мишка не двигался. \"Ой, как же я его сниму?\" - подумала Маша.\n\nВдруг, Маша увидела, что мишка дергает за ниточку на кресле! Ниточка была длинная, как хвост у кошки. Маша дернула ниточку, и кресло начало двигаться!\n\nКресло покатилось, а мишка остался сидеть на нем. Маша засмеялась. \"Вот так! Я не дергала мишку, а дергала кресло!\"\n\nМаша поняла, что не всегда нужно дергать то, что хочется. Иногда нужно подумать, как сделать по-другому.", "verb": "дергать"}