{"adjective": "гладкий", "features": ["иметь неожиданный поворот сюжета", "быть поучительным", "содержать диалог", "иметь трёх персонажей"], "model": "google/gemma-2-27b-it bnb_4bit", "noun": "страна", "sha3_256": "ef3f05beb3e99ca4d262e1c79e29587d3fea7475e3694901545dbd27dd9052b7", "story": "Жила-была маленькая лисичка. Она любила играть с мячиком. Однажды лисичка катила мячик по гладкой дорожке. Вдруг мячик укатился далеко-далеко, в страну игрушек!\n\nЛисичка побежала за мячиком и увидела двух мишек. Они сидели на скамейке и визжали от смеха. \"Что случилось?\" - спросила лисичка. \"Мы потеряли свой любимый кубик!\" - ответили мишки.\n\nЛисичка посмотрела на землю и увидела кубик! Он был спрятан под листом. \"Вот ваш кубик!\" - сказала лисичка, и отдала его мишкам. Мишки обрадовались и стали играть с лисичкой и мячиком.\n\nЛисичка поняла, что помогать другим - это очень приятно. Иногда, когда ты помогаешь, ты получаешь еще больше радости, чем от игры.", "verb": "визжать"}