{"adjective": "лающий", "features": ["плохо заканчиваться", "быть поучительным", "иметь двух персонажей"], "model": "google/gemma-2-27b-it bnb_4bit", "noun": "сарай", "sha3_256": "f1cadded0db5ce5f4405a44abc3afb4abdac0cd647c3cffcf6d008106ad1cb00", "story": "Маша и ее щенок, Дружок, играли в саду. Дружок бегал за бабочками, а Маша собирала цветы. Солнце светило ярко, и Маша стала дышать тяжело.\n\n\"Дружок, пойдем в сарай,\" - сказала Маша. \"Там прохладно.\" Дружок лаял и бегал кругами. Он не хотел идти в сарай.\n\nМаша вошла в сарай. Там было темно и тихо. Маша села на сено и стала дышать спокойно. Но Дружок остался снаружи.\n\nМаша услышала лающий голос Дружка. Он лаял и лаял, и Маша поняла, что он испугался. Маша вышла из сарая, но Дружок убежал. Маша не знала, где он.\n\nМаша заплакала. Она поняла, что не должна была оставлять Дружка одного. Теперь он потерялся, и Маша очень грустила.", "verb": "дышать"}