{"adjective": "волнующий", "features": ["быть похожим на сказку", "иметь одного персонажа", "плохо заканчиваться"], "model": "google/gemma-2-27b-it bnb_4bit", "noun": "расставание", "sha3_256": "f3cc07fff199438876c5fe483c27286b099181da90721c75372279403d8ceb64", "story": "Жила-была маленькая рыбка по имени Плюшка. Плюшка любила плавать в синем озере. Она грести плавниками, нырять и играть с другими рыбками. Но однажды Плюшка увидела большую лодку. Лодка плыла по озеру и гребла веслами. Плюшка никогда не видела такой большой лодки.\n\nРыбка Плюшка решила поплыть к лодке. Она хотела посмотреть, что там происходит. Плюшка плыла и плыла, пока не оказалась совсем близко к лодке. Но вдруг, лодка резко повернула и уплыла прочь. Плюшка хотела догнать лодку, но она плыла слишком быстро.\n\nПлюшка грустно смотрела, как лодка исчезает вдали. Она очень хотела узнать, что там было в лодке. Расставание с лодкой было волнующим, но грустным. Плюшка вернулась к своим друзьям, но грусть не покидала ее.\n\nТеперь Плюшка часто смотрела на горизонт, надеясь увидеть лодку снова. Но лодка больше не появлялась. Плюшка грустила, что не успела узнать, что там было в лодке.", "verb": "грести"}