{"adjective": "прелестный", "features": ["иметь неожиданный поворот сюжета", "быть поучительным"], "model": "google/gemma-2-27b-it bnb_4bit", "noun": "карандаш", "sha3_256": "fb54c949745ebbd0ffc8cd28995d056c6dee3f22b105088768b93ce5e3a074a3", "story": "Маша играла с своим прелестным карандашом. Он был красный, как яблоко, и Маша любила рисовать им солнышко. Маша рисовала солнышко, а потом оно стало большим и большим, пока не заполнило весь лист бумаги!\n\nМаша захотела нарисовать еще одно солнышко, но карандаш не хотел рисовать. Он возражал! Маша пыталась нарисовать, но карандаш просто царапал бумагу.\n\nМаша расстроилась. Она не понимала, почему карандаш не хочет рисовать. Вдруг, мама подошла к Маше и сказала: \"Маша, карандаш устал. Он рисовал много солнышек, и теперь ему нужно отдохнуть\".\n\nМаша поняла. Она взяла карандаш и положила его на стол. \"Спасибо за солнышки,\" - сказала Маша карандашу. \"Теперь ты можешь отдохнуть\". Маша решила поиграть с мишкой, пока карандаш не будет готов рисовать снова.", "verb": "возражать"}