{"adjective": "неприятный", "features": ["быть поучительным", "иметь двух персонажей", "плохо заканчиваться"], "model": "google/gemma-2-27b-it bnb_4bit", "noun": "кровать", "sha3_256": "fd51e8379aabd58ce6ee85981038caacd04e55495402c01037a04fbbc4d7e496", "story": "Маша играла с мишкой на кровати. Она прыгала и прыгала, и мишка тоже прыгал. Маша захотела перевернуть мишку, чтобы он смотрел вверх. Она взяла мишку и перевернула его.\n\nВдруг Маша услышала странный звук. Кровать качнулась, и Маша упала! Она ударилась головой о пол. Маша заплакала.\n\nМама услышала плач и побежала в комнату. Она увидела Машу на полу и сразу поняла, что случилось. Мама взяла Машу на руки и сказала: \"Нельзя перевертывать кровать! Это опасно!\".\n\nМаша заплакала еще сильнее. Мама обняла ее и сказала: \"Мы пойдем к врачу, чтобы он посмотрел твою головку\". Маша знала, что сделала что-то неприятное. Она больше не хотела перевертывать кровать.", "verb": "переворачивать"}